fuzzy_multi_dict/__init__.py
fuzzy_multi_dict/fuzzy_multi_dict.py
fuzzy_multi_dict-0.0.7.dist-info/LICENSE
fuzzy_multi_dict-0.0.7.dist-info/WHEEL
fuzzy_multi_dict-0.0.7.dist-info/METADATA
fuzzy_multi_dict-0.0.7.dist-info/RECORD
