Metadata-Version: 2.1
Name: fuzzy-multi-dict
Version: 0.0.7
Summary: `fuzzy-multi-dict` is a module that provides a hight-flexible structure for storing and accessing information by a string key.
License: LICENSE
Author: Tetiana Lytvynenko
Author-email: lytvynenkotv@gmail.com
Requires-Python: >=3.9,<4.0
Classifier: License :: Other/Proprietary License
Classifier: Programming Language :: Python :: 3
Classifier: Programming Language :: Python :: 3.9
Classifier: Programming Language :: Python :: 3.10
Classifier: Programming Language :: Python :: 3.11
Requires-Dist: dill (==0.3.7)
